{
  "puzzle": {
    "puzzle_id": 3826,
    "date": "2025-06-17",
    "formatted_date": "Tuesday, June 17, 2025",
    "title": "New York Times, Tuesday, June 17, 2025",
    "author": "Tarun Krishnamurthy",
    "editor": "Will Shortz",
    "day_of_week": "Tuesday",
    "permalink": "https://www.xwordinfo.com/Crossword?date=06/17/2025",
    "created_at": "2025-06-17 04:30:56"
  },
  "clues": [
    {
      "clue_id": 314249,
      "puzzle_id": 3826,
      "number": 1,
      "direction": "across",
      "clue_text": "Ride-or-dies, in brief",
      "answer": "BFFS"
    },
    {
      "clue_id": 314250,
      "puzzle_id": 3826,
      "number": 5,
      "direction": "across",
      "clue_text": "Healthy ones may be square",
      "answer": "MEALS"
    },
    {
      "clue_id": 314251,
      "puzzle_id": 3826,
      "number": 10,
      "direction": "across",
      "clue_text": "Lively party",
      "answer": "BASH"
    },
    {
      "clue_id": 314252,
      "puzzle_id": 3826,
      "number": 14,
      "direction": "across",
      "clue_text": "Came down to earth",
      "answer": "ALIT"
    },
    {
      "clue_id": 314253,
      "puzzle_id": 3826,
      "number": 15,
      "direction": "across",
      "clue_text": "Skate park trick",
      "answer": "OLLIE"
    },
    {
      "clue_id": 314254,
      "puzzle_id": 3826,
      "number": 16,
      "direction": "across",
      "clue_text": "Defaulter's loss, in brief",
      "answer": "REPO"
    },
    {
      "clue_id": 314255,
      "puzzle_id": 3826,
      "number": 17,
      "direction": "across",
      "clue_text": "Classic Beatles song written and sung by George Harrison",
      "answer": "HERECOMESTHESUN"
    },
    {
      "clue_id": 314256,
      "puzzle_id": 3826,
      "number": 20,
      "direction": "across",
      "clue_text": "Windstorm often accompanied by rain",
      "answer": "TEMPEST"
    },
    {
      "clue_id": 314257,
      "puzzle_id": 3826,
      "number": 21,
      "direction": "across",
      "clue_text": "Shakespeare's Globe, e.g.",
      "answer": "THEATRE"
    },
    {
      "clue_id": 314258,
      "puzzle_id": 3826,
      "number": 22,
      "direction": "across",
      "clue_text": "Auction offer",
      "answer": "BID"
    },
    {
      "clue_id": 314259,
      "puzzle_id": 3826,
      "number": 23,
      "direction": "across",
      "clue_text": "Outdoor gear giant",
      "answer": "REI"
    },
    {
      "clue_id": 314260,
      "puzzle_id": 3826,
      "number": 25,
      "direction": "across",
      "clue_text": "Volcanic output",
      "answer": "ASH"
    },
    {
      "clue_id": 314261,
      "puzzle_id": 3826,
      "number": 26,
      "direction": "across",
      "clue_text": "Mathematician/philosopher who wrote \"I think, therefore I am\"",
      "answer": "RENEDESCARTES"
    },
    {
      "clue_id": 314262,
      "puzzle_id": 3826,
      "number": 30,
      "direction": "across",
      "clue_text": "Sidekick",
      "answer": "PAL"
    },
    {
      "clue_id": 314263,
      "puzzle_id": 3826,
      "number": 31,
      "direction": "across",
      "clue_text": "Talks in all caps, say",
      "answer": "YELLS"
    },
    {
      "clue_id": 314264,
      "puzzle_id": 3826,
      "number": 32,
      "direction": "across",
      "clue_text": "Pedicured digit",
      "answer": "TOE"
    },
    {
      "clue_id": 314265,
      "puzzle_id": 3826,
      "number": 34,
      "direction": "across",
      "clue_text": "Pilots a plane",
      "answer": "AVIATES"
    },
    {
      "clue_id": 314266,
      "puzzle_id": 3826,
      "number": 37,
      "direction": "across",
      "clue_text": "Experience humiliation",
      "answer": "EATDIRT"
    },
    {
      "clue_id": 314267,
      "puzzle_id": 3826,
      "number": 40,
      "direction": "across",
      "clue_text": "With 41-Across, popular candy represented by the circled letters in 17-, 26- and 57-Across?",
      "answer": "REESES"
    },
    {
      "clue_id": 314268,
      "puzzle_id": 3826,
      "number": 41,
      "direction": "across",
      "clue_text": "See 40-Across",
      "answer": "PIECES"
    },
    {
      "clue_id": 314269,
      "puzzle_id": 3826,
      "number": 42,
      "direction": "across",
      "clue_text": "Like Santa's helpers",
      "answer": "ELFIN"
    },
    {
      "clue_id": 314270,
      "puzzle_id": 3826,
      "number": 43,
      "direction": "across",
      "clue_text": "Many an I.R.S. employee",
      "answer": "CPA"
    },
    {
      "clue_id": 314271,
      "puzzle_id": 3826,
      "number": 46,
      "direction": "across",
      "clue_text": "Like many dorm rooms",
      "answer": "MESSY"
    },
    {
      "clue_id": 314272,
      "puzzle_id": 3826,
      "number": 50,
      "direction": "across",
      "clue_text": "Shady, in modern lingo",
      "answer": "SUS"
    },
    {
      "clue_id": 314273,
      "puzzle_id": 3826,
      "number": 54,
      "direction": "across",
      "clue_text": "Insta upload",
      "answer": "PIC"
    },
    {
      "clue_id": 314274,
      "puzzle_id": 3826,
      "number": 57,
      "direction": "across",
      "clue_text": "Does some door-to-door campaigning",
      "answer": "PRESSESTHEFLESH"
    },
    {
      "clue_id": 314275,
      "puzzle_id": 3826,
      "number": 60,
      "direction": "across",
      "clue_text": "Own up to",
      "answer": "ADMIT"
    },
    {
      "clue_id": 314276,
      "puzzle_id": 3826,
      "number": 61,
      "direction": "across",
      "clue_text": "Reason for overtime",
      "answer": "TIE"
    },
    {
      "clue_id": 314277,
      "puzzle_id": 3826,
      "number": 62,
      "direction": "across",
      "clue_text": "Bloke",
      "answer": "FELLA"
    },
    {
      "clue_id": 314278,
      "puzzle_id": 3826,
      "number": 63,
      "direction": "across",
      "clue_text": "Spades or diamonds",
      "answer": "SUIT"
    },
    {
      "clue_id": 314279,
      "puzzle_id": 3826,
      "number": 64,
      "direction": "across",
      "clue_text": "\"Chandelier\" singer, 2014",
      "answer": "SIA"
    },
    {
      "clue_id": 314280,
      "puzzle_id": 3826,
      "number": 65,
      "direction": "across",
      "clue_text": "Typical high school student ... like this puzzle's constructor!",
      "answer": "TEEN"
    },
    {
      "clue_id": 314281,
      "puzzle_id": 3826,
      "number": 1,
      "direction": "down",
      "clue_text": "Money in Thailand",
      "answer": "BAHT"
    },
    {
      "clue_id": 314282,
      "puzzle_id": 3826,
      "number": 2,
      "direction": "down",
      "clue_text": "Skedaddle",
      "answer": "FLEE"
    },
    {
      "clue_id": 314283,
      "puzzle_id": 3826,
      "number": 4,
      "direction": "down",
      "clue_text": "Intervene",
      "answer": "STEPIN"
    },
    {
      "clue_id": 314284,
      "puzzle_id": 3826,
      "number": 5,
      "direction": "down",
      "clue_text": "Cattle calls",
      "answer": "MOOS"
    },
    {
      "clue_id": 314285,
      "puzzle_id": 3826,
      "number": 6,
      "direction": "down",
      "clue_text": "Street liners in parts of New England",
      "answer": "ELMTREES"
    },
    {
      "clue_id": 314286,
      "puzzle_id": 3826,
      "number": 7,
      "direction": "down",
      "clue_text": "Word after ginger or pale",
      "answer": "ALE"
    },
    {
      "clue_id": 314287,
      "puzzle_id": 3826,
      "number": 8,
      "direction": "down",
      "clue_text": "Online post whose title may begin \"The Top 10 Best ...\"",
      "answer": "LISTICLE"
    },
    {
      "clue_id": 314288,
      "puzzle_id": 3826,
      "number": 9,
      "direction": "down",
      "clue_text": "Rogen of \"The Studio\" and \"The Interview\"",
      "answer": "SETH"
    },
    {
      "clue_id": 314289,
      "puzzle_id": 3826,
      "number": 10,
      "direction": "down",
      "clue_text": "Choice at KFC",
      "answer": "BREAST"
    },
    {
      "clue_id": 314290,
      "puzzle_id": 3826,
      "number": 11,
      "direction": "down",
      "clue_text": "They're a matter of taste",
      "answer": "AESTHETICS"
    },
    {
      "clue_id": 314291,
      "puzzle_id": 3826,
      "number": 12,
      "direction": "down",
      "clue_text": "Cowboy boot attachment",
      "answer": "SPUR"
    },
    {
      "clue_id": 314292,
      "puzzle_id": 3826,
      "number": 13,
      "direction": "down",
      "clue_text": "Sharpen, as skills",
      "answer": "HONE"
    },
    {
      "clue_id": 314293,
      "puzzle_id": 3826,
      "number": 18,
      "direction": "down",
      "clue_text": "Surrender",
      "answer": "CEDE"
    },
    {
      "clue_id": 314294,
      "puzzle_id": 3826,
      "number": 19,
      "direction": "down",
      "clue_text": "Learn by word of mouth",
      "answer": "HEAR"
    },
    {
      "clue_id": 314295,
      "puzzle_id": 3826,
      "number": 24,
      "direction": "down",
      "clue_text": "Subj. for some new U.S. residents",
      "answer": "ESL"
    },
    {
      "clue_id": 314296,
      "puzzle_id": 3826,
      "number": 26,
      "direction": "down",
      "clue_text": "Get tangled up",
      "answer": "RAVEL"
    },
    {
      "clue_id": 314297,
      "puzzle_id": 3826,
      "number": 27,
      "direction": "down",
      "clue_text": "Easter egg colorings",
      "answer": "DYES"
    },
    {
      "clue_id": 314298,
      "puzzle_id": 3826,
      "number": 28,
      "direction": "down",
      "clue_text": "\"Make it snappy!\"",
      "answer": "ASAP"
    },
    {
      "clue_id": 314299,
      "puzzle_id": 3826,
      "number": 29,
      "direction": "down",
      "clue_text": "Sensitive skin spots",
      "answer": "SORES"
    },
    {
      "clue_id": 314300,
      "puzzle_id": 3826,
      "number": 30,
      "direction": "down",
      "clue_text": "Cut back",
      "answer": "PARE"
    },
    {
      "clue_id": 314301,
      "puzzle_id": 3826,
      "number": 33,
      "direction": "down",
      "clue_text": "Handicrafts site",
      "answer": "ETSY"
    },
    {
      "clue_id": 314302,
      "puzzle_id": 3826,
      "number": 35,
      "direction": "down",
      "clue_text": "Garage sale caveat",
      "answer": "ASIS"
    },
    {
      "clue_id": 314303,
      "puzzle_id": 3826,
      "number": 36,
      "direction": "down",
      "clue_text": "A sixth of the way through the hour",
      "answer": "TENPAST"
    },
    {
      "clue_id": 314304,
      "puzzle_id": 3826,
      "number": 38,
      "direction": "down",
      "clue_text": "R&R",
      "answer": "TIMEOFF"
    },
    {
      "clue_id": 314305,
      "puzzle_id": 3826,
      "number": 39,
      "direction": "down",
      "clue_text": "Proof of ownership",
      "answer": "DEED"
    },
    {
      "clue_id": 314306,
      "puzzle_id": 3826,
      "number": 43,
      "direction": "down",
      "clue_text": "Wave peaks",
      "answer": "CRESTS"
    },
    {
      "clue_id": 314307,
      "puzzle_id": 3826,
      "number": 44,
      "direction": "down",
      "clue_text": "Sequel title ender",
      "answer": "PARTII"
    },
    {
      "clue_id": 314308,
      "puzzle_id": 3826,
      "number": 45,
      "direction": "down",
      "clue_text": "Tennis's Gibson who won back-to-back Wimbledons and U.S. Opens",
      "answer": "ALTHEA"
    },
    {
      "clue_id": 314309,
      "puzzle_id": 3826,
      "number": 48,
      "direction": "down",
      "clue_text": "Suffix with percent",
      "answer": "ILE"
    },
    {
      "clue_id": 314310,
      "puzzle_id": 3826,
      "number": 49,
      "direction": "down",
      "clue_text": "Wireless standard inits.",
      "answer": "LTE"
    },
    {
      "clue_id": 314311,
      "puzzle_id": 3826,
      "number": 50,
      "direction": "down",
      "clue_text": "Relaxing retreats",
      "answer": "SPAS"
    },
    {
      "clue_id": 314312,
      "puzzle_id": 3826,
      "number": 51,
      "direction": "down",
      "clue_text": "Language in which the first four counting numbers are ek, do, tin, char",
      "answer": "URDU"
    },
    {
      "clue_id": 314313,
      "puzzle_id": 3826,
      "number": 52,
      "direction": "down",
      "clue_text": "18-wheeler",
      "answer": "SEMI"
    },
    {
      "clue_id": 314314,
      "puzzle_id": 3826,
      "number": 54,
      "direction": "down",
      "clue_text": "Sports star who debuted with the New York Cosmos in 1975",
      "answer": "PELE"
    },
    {
      "clue_id": 314315,
      "puzzle_id": 3826,
      "number": 55,
      "direction": "down",
      "clue_text": "Tahiti, e.g.",
      "answer": "ISLE"
    },
    {
      "clue_id": 314316,
      "puzzle_id": 3826,
      "number": 56,
      "direction": "down",
      "clue_text": "Jackie of \"Rush Hour\"",
      "answer": "CHAN"
    },
    {
      "clue_id": 314317,
      "puzzle_id": 3826,
      "number": 58,
      "direction": "down",
      "clue_text": "Host's directive to a guest",
      "answer": "SIT"
    },
    {
      "clue_id": 314318,
      "puzzle_id": 3826,
      "number": 59,
      "direction": "down",
      "clue_text": "Tennis do-over",
      "answer": "LET"
    }
  ],
  "across": [
    {
      "clue_id": 314249,
      "puzzle_id": 3826,
      "number": 1,
      "direction": "across",
      "clue_text": "Ride-or-dies, in brief",
      "answer": "BFFS"
    },
    {
      "clue_id": 314250,
      "puzzle_id": 3826,
      "number": 5,
      "direction": "across",
      "clue_text": "Healthy ones may be square",
      "answer": "MEALS"
    },
    {
      "clue_id": 314251,
      "puzzle_id": 3826,
      "number": 10,
      "direction": "across",
      "clue_text": "Lively party",
      "answer": "BASH"
    },
    {
      "clue_id": 314252,
      "puzzle_id": 3826,
      "number": 14,
      "direction": "across",
      "clue_text": "Came down to earth",
      "answer": "ALIT"
    },
    {
      "clue_id": 314253,
      "puzzle_id": 3826,
      "number": 15,
      "direction": "across",
      "clue_text": "Skate park trick",
      "answer": "OLLIE"
    },
    {
      "clue_id": 314254,
      "puzzle_id": 3826,
      "number": 16,
      "direction": "across",
      "clue_text": "Defaulter's loss, in brief",
      "answer": "REPO"
    },
    {
      "clue_id": 314255,
      "puzzle_id": 3826,
      "number": 17,
      "direction": "across",
      "clue_text": "Classic Beatles song written and sung by George Harrison",
      "answer": "HERECOMESTHESUN"
    },
    {
      "clue_id": 314256,
      "puzzle_id": 3826,
      "number": 20,
      "direction": "across",
      "clue_text": "Windstorm often accompanied by rain",
      "answer": "TEMPEST"
    },
    {
      "clue_id": 314257,
      "puzzle_id": 3826,
      "number": 21,
      "direction": "across",
      "clue_text": "Shakespeare's Globe, e.g.",
      "answer": "THEATRE"
    },
    {
      "clue_id": 314258,
      "puzzle_id": 3826,
      "number": 22,
      "direction": "across",
      "clue_text": "Auction offer",
      "answer": "BID"
    },
    {
      "clue_id": 314259,
      "puzzle_id": 3826,
      "number": 23,
      "direction": "across",
      "clue_text": "Outdoor gear giant",
      "answer": "REI"
    },
    {
      "clue_id": 314260,
      "puzzle_id": 3826,
      "number": 25,
      "direction": "across",
      "clue_text": "Volcanic output",
      "answer": "ASH"
    },
    {
      "clue_id": 314261,
      "puzzle_id": 3826,
      "number": 26,
      "direction": "across",
      "clue_text": "Mathematician/philosopher who wrote \"I think, therefore I am\"",
      "answer": "RENEDESCARTES"
    },
    {
      "clue_id": 314262,
      "puzzle_id": 3826,
      "number": 30,
      "direction": "across",
      "clue_text": "Sidekick",
      "answer": "PAL"
    },
    {
      "clue_id": 314263,
      "puzzle_id": 3826,
      "number": 31,
      "direction": "across",
      "clue_text": "Talks in all caps, say",
      "answer": "YELLS"
    },
    {
      "clue_id": 314264,
      "puzzle_id": 3826,
      "number": 32,
      "direction": "across",
      "clue_text": "Pedicured digit",
      "answer": "TOE"
    },
    {
      "clue_id": 314265,
      "puzzle_id": 3826,
      "number": 34,
      "direction": "across",
      "clue_text": "Pilots a plane",
      "answer": "AVIATES"
    },
    {
      "clue_id": 314266,
      "puzzle_id": 3826,
      "number": 37,
      "direction": "across",
      "clue_text": "Experience humiliation",
      "answer": "EATDIRT"
    },
    {
      "clue_id": 314267,
      "puzzle_id": 3826,
      "number": 40,
      "direction": "across",
      "clue_text": "With 41-Across, popular candy represented by the circled letters in 17-, 26- and 57-Across?",
      "answer": "REESES"
    },
    {
      "clue_id": 314268,
      "puzzle_id": 3826,
      "number": 41,
      "direction": "across",
      "clue_text": "See 40-Across",
      "answer": "PIECES"
    },
    {
      "clue_id": 314269,
      "puzzle_id": 3826,
      "number": 42,
      "direction": "across",
      "clue_text": "Like Santa's helpers",
      "answer": "ELFIN"
    },
    {
      "clue_id": 314270,
      "puzzle_id": 3826,
      "number": 43,
      "direction": "across",
      "clue_text": "Many an I.R.S. employee",
      "answer": "CPA"
    },
    {
      "clue_id": 314271,
      "puzzle_id": 3826,
      "number": 46,
      "direction": "across",
      "clue_text": "Like many dorm rooms",
      "answer": "MESSY"
    },
    {
      "clue_id": 314272,
      "puzzle_id": 3826,
      "number": 50,
      "direction": "across",
      "clue_text": "Shady, in modern lingo",
      "answer": "SUS"
    },
    {
      "clue_id": 314273,
      "puzzle_id": 3826,
      "number": 54,
      "direction": "across",
      "clue_text": "Insta upload",
      "answer": "PIC"
    },
    {
      "clue_id": 314274,
      "puzzle_id": 3826,
      "number": 57,
      "direction": "across",
      "clue_text": "Does some door-to-door campaigning",
      "answer": "PRESSESTHEFLESH"
    },
    {
      "clue_id": 314275,
      "puzzle_id": 3826,
      "number": 60,
      "direction": "across",
      "clue_text": "Own up to",
      "answer": "ADMIT"
    },
    {
      "clue_id": 314276,
      "puzzle_id": 3826,
      "number": 61,
      "direction": "across",
      "clue_text": "Reason for overtime",
      "answer": "TIE"
    },
    {
      "clue_id": 314277,
      "puzzle_id": 3826,
      "number": 62,
      "direction": "across",
      "clue_text": "Bloke",
      "answer": "FELLA"
    },
    {
      "clue_id": 314278,
      "puzzle_id": 3826,
      "number": 63,
      "direction": "across",
      "clue_text": "Spades or diamonds",
      "answer": "SUIT"
    },
    {
      "clue_id": 314279,
      "puzzle_id": 3826,
      "number": 64,
      "direction": "across",
      "clue_text": "\"Chandelier\" singer, 2014",
      "answer": "SIA"
    },
    {
      "clue_id": 314280,
      "puzzle_id": 3826,
      "number": 65,
      "direction": "across",
      "clue_text": "Typical high school student ... like this puzzle's constructor!",
      "answer": "TEEN"
    }
  ],
  "down": [
    {
      "clue_id": 314281,
      "puzzle_id": 3826,
      "number": 1,
      "direction": "down",
      "clue_text": "Money in Thailand",
      "answer": "BAHT"
    },
    {
      "clue_id": 314282,
      "puzzle_id": 3826,
      "number": 2,
      "direction": "down",
      "clue_text": "Skedaddle",
      "answer": "FLEE"
    },
    {
      "clue_id": 314283,
      "puzzle_id": 3826,
      "number": 4,
      "direction": "down",
      "clue_text": "Intervene",
      "answer": "STEPIN"
    },
    {
      "clue_id": 314284,
      "puzzle_id": 3826,
      "number": 5,
      "direction": "down",
      "clue_text": "Cattle calls",
      "answer": "MOOS"
    },
    {
      "clue_id": 314285,
      "puzzle_id": 3826,
      "number": 6,
      "direction": "down",
      "clue_text": "Street liners in parts of New England",
      "answer": "ELMTREES"
    },
    {
      "clue_id": 314286,
      "puzzle_id": 3826,
      "number": 7,
      "direction": "down",
      "clue_text": "Word after ginger or pale",
      "answer": "ALE"
    },
    {
      "clue_id": 314287,
      "puzzle_id": 3826,
      "number": 8,
      "direction": "down",
      "clue_text": "Online post whose title may begin \"The Top 10 Best ...\"",
      "answer": "LISTICLE"
    },
    {
      "clue_id": 314288,
      "puzzle_id": 3826,
      "number": 9,
      "direction": "down",
      "clue_text": "Rogen of \"The Studio\" and \"The Interview\"",
      "answer": "SETH"
    },
    {
      "clue_id": 314289,
      "puzzle_id": 3826,
      "number": 10,
      "direction": "down",
      "clue_text": "Choice at KFC",
      "answer": "BREAST"
    },
    {
      "clue_id": 314290,
      "puzzle_id": 3826,
      "number": 11,
      "direction": "down",
      "clue_text": "They're a matter of taste",
      "answer": "AESTHETICS"
    },
    {
      "clue_id": 314291,
      "puzzle_id": 3826,
      "number": 12,
      "direction": "down",
      "clue_text": "Cowboy boot attachment",
      "answer": "SPUR"
    },
    {
      "clue_id": 314292,
      "puzzle_id": 3826,
      "number": 13,
      "direction": "down",
      "clue_text": "Sharpen, as skills",
      "answer": "HONE"
    },
    {
      "clue_id": 314293,
      "puzzle_id": 3826,
      "number": 18,
      "direction": "down",
      "clue_text": "Surrender",
      "answer": "CEDE"
    },
    {
      "clue_id": 314294,
      "puzzle_id": 3826,
      "number": 19,
      "direction": "down",
      "clue_text": "Learn by word of mouth",
      "answer": "HEAR"
    },
    {
      "clue_id": 314295,
      "puzzle_id": 3826,
      "number": 24,
      "direction": "down",
      "clue_text": "Subj. for some new U.S. residents",
      "answer": "ESL"
    },
    {
      "clue_id": 314296,
      "puzzle_id": 3826,
      "number": 26,
      "direction": "down",
      "clue_text": "Get tangled up",
      "answer": "RAVEL"
    },
    {
      "clue_id": 314297,
      "puzzle_id": 3826,
      "number": 27,
      "direction": "down",
      "clue_text": "Easter egg colorings",
      "answer": "DYES"
    },
    {
      "clue_id": 314298,
      "puzzle_id": 3826,
      "number": 28,
      "direction": "down",
      "clue_text": "\"Make it snappy!\"",
      "answer": "ASAP"
    },
    {
      "clue_id": 314299,
      "puzzle_id": 3826,
      "number": 29,
      "direction": "down",
      "clue_text": "Sensitive skin spots",
      "answer": "SORES"
    },
    {
      "clue_id": 314300,
      "puzzle_id": 3826,
      "number": 30,
      "direction": "down",
      "clue_text": "Cut back",
      "answer": "PARE"
    },
    {
      "clue_id": 314301,
      "puzzle_id": 3826,
      "number": 33,
      "direction": "down",
      "clue_text": "Handicrafts site",
      "answer": "ETSY"
    },
    {
      "clue_id": 314302,
      "puzzle_id": 3826,
      "number": 35,
      "direction": "down",
      "clue_text": "Garage sale caveat",
      "answer": "ASIS"
    },
    {
      "clue_id": 314303,
      "puzzle_id": 3826,
      "number": 36,
      "direction": "down",
      "clue_text": "A sixth of the way through the hour",
      "answer": "TENPAST"
    },
    {
      "clue_id": 314304,
      "puzzle_id": 3826,
      "number": 38,
      "direction": "down",
      "clue_text": "R&R",
      "answer": "TIMEOFF"
    },
    {
      "clue_id": 314305,
      "puzzle_id": 3826,
      "number": 39,
      "direction": "down",
      "clue_text": "Proof of ownership",
      "answer": "DEED"
    },
    {
      "clue_id": 314306,
      "puzzle_id": 3826,
      "number": 43,
      "direction": "down",
      "clue_text": "Wave peaks",
      "answer": "CRESTS"
    },
    {
      "clue_id": 314307,
      "puzzle_id": 3826,
      "number": 44,
      "direction": "down",
      "clue_text": "Sequel title ender",
      "answer": "PARTII"
    },
    {
      "clue_id": 314308,
      "puzzle_id": 3826,
      "number": 45,
      "direction": "down",
      "clue_text": "Tennis's Gibson who won back-to-back Wimbledons and U.S. Opens",
      "answer": "ALTHEA"
    },
    {
      "clue_id": 314309,
      "puzzle_id": 3826,
      "number": 48,
      "direction": "down",
      "clue_text": "Suffix with percent",
      "answer": "ILE"
    },
    {
      "clue_id": 314310,
      "puzzle_id": 3826,
      "number": 49,
      "direction": "down",
      "clue_text": "Wireless standard inits.",
      "answer": "LTE"
    },
    {
      "clue_id": 314311,
      "puzzle_id": 3826,
      "number": 50,
      "direction": "down",
      "clue_text": "Relaxing retreats",
      "answer": "SPAS"
    },
    {
      "clue_id": 314312,
      "puzzle_id": 3826,
      "number": 51,
      "direction": "down",
      "clue_text": "Language in which the first four counting numbers are ek, do, tin, char",
      "answer": "URDU"
    },
    {
      "clue_id": 314313,
      "puzzle_id": 3826,
      "number": 52,
      "direction": "down",
      "clue_text": "18-wheeler",
      "answer": "SEMI"
    },
    {
      "clue_id": 314314,
      "puzzle_id": 3826,
      "number": 54,
      "direction": "down",
      "clue_text": "Sports star who debuted with the New York Cosmos in 1975",
      "answer": "PELE"
    },
    {
      "clue_id": 314315,
      "puzzle_id": 3826,
      "number": 55,
      "direction": "down",
      "clue_text": "Tahiti, e.g.",
      "answer": "ISLE"
    },
    {
      "clue_id": 314316,
      "puzzle_id": 3826,
      "number": 56,
      "direction": "down",
      "clue_text": "Jackie of \"Rush Hour\"",
      "answer": "CHAN"
    },
    {
      "clue_id": 314317,
      "puzzle_id": 3826,
      "number": 58,
      "direction": "down",
      "clue_text": "Host's directive to a guest",
      "answer": "SIT"
    },
    {
      "clue_id": 314318,
      "puzzle_id": 3826,
      "number": 59,
      "direction": "down",
      "clue_text": "Tennis do-over",
      "answer": "LET"
    }
  ]
}