{
  "success": true,
  "data": {
    "puzzle": {
      "date": "2026-01-29",
      "formatted_date": "Thursday, January 29, 2026",
      "day_of_week": "Thursday",
      "title": "New York Times, Thursday, January 29, 2026",
      "author": "",
      "editor": ""
    },
    "clues": [
      {
        "number": 1,
        "clue": "Vehicle in which it's often legal to drink alcohol",
        "answer": "LIMO",
        "direction": "across"
      },
      {
        "number": 5,
        "clue": "Jokesters",
        "answer": "WAGS",
        "direction": "across"
      },
      {
        "number": 9,
        "clue": "Moistens, as a fern",
        "answer": "MISTS",
        "direction": "across"
      },
      {
        "number": 14,
        "clue": "First lady's partner",
        "answer": "ADAM",
        "direction": "across"
      },
      {
        "number": 15,
        "clue": "Object of veneration",
        "answer": "IDOL",
        "direction": "across"
      },
      {
        "number": 16,
        "clue": "Oft-disparaged family member",
        "answer": "INLAW",
        "direction": "across"
      },
      {
        "number": 17,
        "clue": "Busiest French airport not serving Paris",
        "answer": "NICE",
        "direction": "across"
      },
      {
        "number": 18,
        "clue": "Prefix with technology",
        "answer": "NANO",
        "direction": "across"
      },
      {
        "number": 19,
        "clue": "Roman goddess often depicted with a bow and arrow",
        "answer": "DIANA",
        "direction": "across"
      },
      {
        "number": 20,
        "clue": "Expand",
        "answer": "GGGGGGGGGGGGGGG",
        "direction": "across"
      },
      {
        "number": 23,
        "clue": "Sonia Sotomayor or Clarence Thomas, once",
        "answer": "YALIE",
        "direction": "across"
      },
      {
        "number": 24,
        "clue": "Abbreviation in a help-wanted ad",
        "answer": "EEO",
        "direction": "across"
      },
      {
        "number": 25,
        "clue": "Part of U.S.N.A.: Abbr.",
        "answer": "NAV",
        "direction": "across"
      },
      {
        "number": 27,
        "clue": "@ @ @",
        "answer": "ATSIGNS",
        "direction": "across"
      },
      {
        "number": 30,
        "clue": "Trippy stuff",
        "answer": "LSD",
        "direction": "across"
      },
      {
        "number": 33,
        "clue": "Folie ___",
        "answer": "ADEUX",
        "direction": "across"
      },
      {
        "number": 35,
        "clue": "Villain portrayer in \"Rocky III\"",
        "answer": "MRT",
        "direction": "across"
      },
      {
        "number": 36,
        "clue": "Lavish celebration",
        "answer": "FETE",
        "direction": "across"
      },
      {
        "number": 37,
        "clue": "Sadness",
        "answer": "SORSORSORSORSOR",
        "direction": "across"
      },
      {
        "number": 41,
        "clue": "Base x height, for a parallelogram",
        "answer": "AREA",
        "direction": "across"
      },
      {
        "number": 42,
        "clue": "Sound made with a wince",
        "answer": "OOF",
        "direction": "across"
      },
      {
        "number": 43,
        "clue": "Extending brim",
        "answer": "VISOR",
        "direction": "across"
      },
      {
        "number": 44,
        "clue": "Guided",
        "answer": "LED",
        "direction": "across"
      },
      {
        "number": 45,
        "clue": "Michigan's historic 1991 basketball team, familiarly",
        "answer": "FABFIVE",
        "direction": "across"
      },
      {
        "number": 48,
        "clue": "Texter's declaration of affection",
        "answer": "ILY",
        "direction": "across"
      },
      {
        "number": 49,
        "clue": "Shags or bobs",
        "answer": "DOS",
        "direction": "across"
      },
      {
        "number": 50,
        "clue": "7-Elevens, e.g.",
        "answer": "MARTS",
        "direction": "across"
      },
      {
        "number": 52,
        "clue": "Day after today",
        "answer": "TOMORTOMORTOMOR",
        "direction": "across"
      },
      {
        "number": 59,
        "clue": "Make a delivery, say",
        "answer": "ORATE",
        "direction": "across"
      },
      {
        "number": 60,
        "clue": "___-golf",
        "answer": "MINI",
        "direction": "across"
      },
      {
        "number": 61,
        "clue": "\"Think again!\"",
        "answer": "NOPE",
        "direction": "across"
      },
      {
        "number": 62,
        "clue": "Lowlands",
        "answer": "DALES",
        "direction": "across"
      },
      {
        "number": 63,
        "clue": "City in NW Pennsylvania",
        "answer": "ERIE",
        "direction": "across"
      },
      {
        "number": 64,
        "clue": "God of war",
        "answer": "ARES",
        "direction": "across"
      },
      {
        "number": 65,
        "clue": "Like some minor celebrities",
        "answer": "DLIST",
        "direction": "across"
      },
      {
        "number": 66,
        "clue": "Five train in Brooklyn",
        "answer": "NETS",
        "direction": "across"
      },
      {
        "number": 67,
        "clue": "Time when one might give up alcohol",
        "answer": "LENT",
        "direction": "across"
      },
      {
        "number": 1,
        "clue": "Clubber ___, \"Rocky III\" villain",
        "answer": "LANG",
        "direction": "down"
      },
      {
        "number": 2,
        "clue": "\"Capisce\"",
        "answer": "IDIG",
        "direction": "down"
      },
      {
        "number": 3,
        "clue": "Like a listening device made out of a paper clip, a plastic straw and seven Lego blocks",
        "answer": "MACGYVERED",
        "direction": "down"
      },
      {
        "number": 4,
        "clue": "Symbol for ohms",
        "answer": "OMEGA",
        "direction": "down"
      },
      {
        "number": 5,
        "clue": "Improvise",
        "answer": "WINGIT",
        "direction": "down"
      },
      {
        "number": 6,
        "clue": "Pithy truths",
        "answer": "ADAGES",
        "direction": "down"
      },
      {
        "number": 7,
        "clue": "Signal to get off the stage, say",
        "answer": "GONG",
        "direction": "down"
      },
      {
        "number": 8,
        "clue": "Arduous journey",
        "answer": "SLOG",
        "direction": "down"
      },
      {
        "number": 9,
        "clue": "Tiny flies",
        "answer": "MIDGES",
        "direction": "down"
      },
      {
        "number": 10,
        "clue": "___ Montoya, \"The Princess Bride\" character",
        "answer": "INIGO",
        "direction": "down"
      },
      {
        "number": 11,
        "clue": "Mining waste",
        "answer": "SLAG",
        "direction": "down"
      },
      {
        "number": 12,
        "clue": "Powdered drink used by NASA",
        "answer": "TANG",
        "direction": "down"
      },
      {
        "number": 13,
        "clue": "Thief's haul",
        "answer": "SWAG",
        "direction": "down"
      },
      {
        "number": 21,
        "clue": "___SmithKline (2000 pharmaceutical merger)",
        "answer": "GLAXO",
        "direction": "down"
      },
      {
        "number": 22,
        "clue": "Chaps",
        "answer": "GENTS",
        "direction": "down"
      },
      {
        "number": 25,
        "clue": "Like some passages",
        "answer": "NASAL",
        "direction": "down"
      },
      {
        "number": 26,
        "clue": "Love, love, love",
        "answer": "ADORE",
        "direction": "down"
      },
      {
        "number": 28,
        "clue": "\"Toodles!\"",
        "answer": "IMOFF",
        "direction": "down"
      },
      {
        "number": 29,
        "clue": "[That makes me so mad!]",
        "answer": "GRR",
        "direction": "down"
      },
      {
        "number": 30,
        "clue": "\"Too many cooks spoil the broth\" principle",
        "answer": "LESSISMORE",
        "direction": "down"
      },
      {
        "number": 31,
        "clue": "Bum's place in a bar",
        "answer": "STOOL",
        "direction": "down"
      },
      {
        "number": 32,
        "clue": "Second-largest city in Northern Ireland",
        "answer": "DERRY",
        "direction": "down"
      },
      {
        "number": 34,
        "clue": "Country that has hosted the most Olympics",
        "answer": "USA",
        "direction": "down"
      },
      {
        "number": 36,
        "clue": "Common day to enjoy Thanksgiving leftovers: Abbr.",
        "answer": "FRI",
        "direction": "down"
      },
      {
        "number": 38,
        "clue": "___ beast (dish in Whoville)",
        "answer": "ROAST",
        "direction": "down"
      },
      {
        "number": 39,
        "clue": "Break down in tears",
        "answer": "SOB",
        "direction": "down"
      },
      {
        "number": 40,
        "clue": "Blindingly obvious",
        "answer": "OVERT",
        "direction": "down"
      },
      {
        "number": 45,
        "clue": "Ranger's domain",
        "answer": "FOREST",
        "direction": "down"
      },
      {
        "number": 46,
        "clue": "\"Leave this to me\"",
        "answer": "IMONIT",
        "direction": "down"
      },
      {
        "number": 47,
        "clue": "Is all over the map",
        "answer": "VARIES",
        "direction": "down"
      },
      {
        "number": 49,
        "clue": "Showers affection (on)",
        "answer": "DOTES",
        "direction": "down"
      },
      {
        "number": 51,
        "clue": "Like the Vietnamese language",
        "answer": "TONAL",
        "direction": "down"
      },
      {
        "number": 52,
        "clue": "Rod Flanders's brother on \"The Simpsons\"",
        "answer": "TODD",
        "direction": "down"
      },
      {
        "number": 53,
        "clue": "Like some traditions",
        "answer": "ORAL",
        "direction": "down"
      },
      {
        "number": 54,
        "clue": "Bamako's land",
        "answer": "MALI",
        "direction": "down"
      },
      {
        "number": 55,
        "clue": "Sign sought by one reading tea leaves",
        "answer": "OMEN",
        "direction": "down"
      },
      {
        "number": 56,
        "clue": "Muck",
        "answer": "MIRE",
        "direction": "down"
      },
      {
        "number": 57,
        "clue": "Major tennis tournament",
        "answer": "OPEN",
        "direction": "down"
      },
      {
        "number": 58,
        "clue": "Pause indicator in sheet music",
        "answer": "REST",
        "direction": "down"
      }
    ],
    "across": [
      {
        "number": 1,
        "clue": "Vehicle in which it's often legal to drink alcohol",
        "answer": "LIMO",
        "direction": "across"
      },
      {
        "number": 5,
        "clue": "Jokesters",
        "answer": "WAGS",
        "direction": "across"
      },
      {
        "number": 9,
        "clue": "Moistens, as a fern",
        "answer": "MISTS",
        "direction": "across"
      },
      {
        "number": 14,
        "clue": "First lady's partner",
        "answer": "ADAM",
        "direction": "across"
      },
      {
        "number": 15,
        "clue": "Object of veneration",
        "answer": "IDOL",
        "direction": "across"
      },
      {
        "number": 16,
        "clue": "Oft-disparaged family member",
        "answer": "INLAW",
        "direction": "across"
      },
      {
        "number": 17,
        "clue": "Busiest French airport not serving Paris",
        "answer": "NICE",
        "direction": "across"
      },
      {
        "number": 18,
        "clue": "Prefix with technology",
        "answer": "NANO",
        "direction": "across"
      },
      {
        "number": 19,
        "clue": "Roman goddess often depicted with a bow and arrow",
        "answer": "DIANA",
        "direction": "across"
      },
      {
        "number": 20,
        "clue": "Expand",
        "answer": "GGGGGGGGGGGGGGG",
        "direction": "across"
      },
      {
        "number": 23,
        "clue": "Sonia Sotomayor or Clarence Thomas, once",
        "answer": "YALIE",
        "direction": "across"
      },
      {
        "number": 24,
        "clue": "Abbreviation in a help-wanted ad",
        "answer": "EEO",
        "direction": "across"
      },
      {
        "number": 25,
        "clue": "Part of U.S.N.A.: Abbr.",
        "answer": "NAV",
        "direction": "across"
      },
      {
        "number": 27,
        "clue": "@ @ @",
        "answer": "ATSIGNS",
        "direction": "across"
      },
      {
        "number": 30,
        "clue": "Trippy stuff",
        "answer": "LSD",
        "direction": "across"
      },
      {
        "number": 33,
        "clue": "Folie ___",
        "answer": "ADEUX",
        "direction": "across"
      },
      {
        "number": 35,
        "clue": "Villain portrayer in \"Rocky III\"",
        "answer": "MRT",
        "direction": "across"
      },
      {
        "number": 36,
        "clue": "Lavish celebration",
        "answer": "FETE",
        "direction": "across"
      },
      {
        "number": 37,
        "clue": "Sadness",
        "answer": "SORSORSORSORSOR",
        "direction": "across"
      },
      {
        "number": 41,
        "clue": "Base x height, for a parallelogram",
        "answer": "AREA",
        "direction": "across"
      },
      {
        "number": 42,
        "clue": "Sound made with a wince",
        "answer": "OOF",
        "direction": "across"
      },
      {
        "number": 43,
        "clue": "Extending brim",
        "answer": "VISOR",
        "direction": "across"
      },
      {
        "number": 44,
        "clue": "Guided",
        "answer": "LED",
        "direction": "across"
      },
      {
        "number": 45,
        "clue": "Michigan's historic 1991 basketball team, familiarly",
        "answer": "FABFIVE",
        "direction": "across"
      },
      {
        "number": 48,
        "clue": "Texter's declaration of affection",
        "answer": "ILY",
        "direction": "across"
      },
      {
        "number": 49,
        "clue": "Shags or bobs",
        "answer": "DOS",
        "direction": "across"
      },
      {
        "number": 50,
        "clue": "7-Elevens, e.g.",
        "answer": "MARTS",
        "direction": "across"
      },
      {
        "number": 52,
        "clue": "Day after today",
        "answer": "TOMORTOMORTOMOR",
        "direction": "across"
      },
      {
        "number": 59,
        "clue": "Make a delivery, say",
        "answer": "ORATE",
        "direction": "across"
      },
      {
        "number": 60,
        "clue": "___-golf",
        "answer": "MINI",
        "direction": "across"
      },
      {
        "number": 61,
        "clue": "\"Think again!\"",
        "answer": "NOPE",
        "direction": "across"
      },
      {
        "number": 62,
        "clue": "Lowlands",
        "answer": "DALES",
        "direction": "across"
      },
      {
        "number": 63,
        "clue": "City in NW Pennsylvania",
        "answer": "ERIE",
        "direction": "across"
      },
      {
        "number": 64,
        "clue": "God of war",
        "answer": "ARES",
        "direction": "across"
      },
      {
        "number": 65,
        "clue": "Like some minor celebrities",
        "answer": "DLIST",
        "direction": "across"
      },
      {
        "number": 66,
        "clue": "Five train in Brooklyn",
        "answer": "NETS",
        "direction": "across"
      },
      {
        "number": 67,
        "clue": "Time when one might give up alcohol",
        "answer": "LENT",
        "direction": "across"
      }
    ],
    "down": [
      {
        "number": 1,
        "clue": "Clubber ___, \"Rocky III\" villain",
        "answer": "LANG",
        "direction": "down"
      },
      {
        "number": 2,
        "clue": "\"Capisce\"",
        "answer": "IDIG",
        "direction": "down"
      },
      {
        "number": 3,
        "clue": "Like a listening device made out of a paper clip, a plastic straw and seven Lego blocks",
        "answer": "MACGYVERED",
        "direction": "down"
      },
      {
        "number": 4,
        "clue": "Symbol for ohms",
        "answer": "OMEGA",
        "direction": "down"
      },
      {
        "number": 5,
        "clue": "Improvise",
        "answer": "WINGIT",
        "direction": "down"
      },
      {
        "number": 6,
        "clue": "Pithy truths",
        "answer": "ADAGES",
        "direction": "down"
      },
      {
        "number": 7,
        "clue": "Signal to get off the stage, say",
        "answer": "GONG",
        "direction": "down"
      },
      {
        "number": 8,
        "clue": "Arduous journey",
        "answer": "SLOG",
        "direction": "down"
      },
      {
        "number": 9,
        "clue": "Tiny flies",
        "answer": "MIDGES",
        "direction": "down"
      },
      {
        "number": 10,
        "clue": "___ Montoya, \"The Princess Bride\" character",
        "answer": "INIGO",
        "direction": "down"
      },
      {
        "number": 11,
        "clue": "Mining waste",
        "answer": "SLAG",
        "direction": "down"
      },
      {
        "number": 12,
        "clue": "Powdered drink used by NASA",
        "answer": "TANG",
        "direction": "down"
      },
      {
        "number": 13,
        "clue": "Thief's haul",
        "answer": "SWAG",
        "direction": "down"
      },
      {
        "number": 21,
        "clue": "___SmithKline (2000 pharmaceutical merger)",
        "answer": "GLAXO",
        "direction": "down"
      },
      {
        "number": 22,
        "clue": "Chaps",
        "answer": "GENTS",
        "direction": "down"
      },
      {
        "number": 25,
        "clue": "Like some passages",
        "answer": "NASAL",
        "direction": "down"
      },
      {
        "number": 26,
        "clue": "Love, love, love",
        "answer": "ADORE",
        "direction": "down"
      },
      {
        "number": 28,
        "clue": "\"Toodles!\"",
        "answer": "IMOFF",
        "direction": "down"
      },
      {
        "number": 29,
        "clue": "[That makes me so mad!]",
        "answer": "GRR",
        "direction": "down"
      },
      {
        "number": 30,
        "clue": "\"Too many cooks spoil the broth\" principle",
        "answer": "LESSISMORE",
        "direction": "down"
      },
      {
        "number": 31,
        "clue": "Bum's place in a bar",
        "answer": "STOOL",
        "direction": "down"
      },
      {
        "number": 32,
        "clue": "Second-largest city in Northern Ireland",
        "answer": "DERRY",
        "direction": "down"
      },
      {
        "number": 34,
        "clue": "Country that has hosted the most Olympics",
        "answer": "USA",
        "direction": "down"
      },
      {
        "number": 36,
        "clue": "Common day to enjoy Thanksgiving leftovers: Abbr.",
        "answer": "FRI",
        "direction": "down"
      },
      {
        "number": 38,
        "clue": "___ beast (dish in Whoville)",
        "answer": "ROAST",
        "direction": "down"
      },
      {
        "number": 39,
        "clue": "Break down in tears",
        "answer": "SOB",
        "direction": "down"
      },
      {
        "number": 40,
        "clue": "Blindingly obvious",
        "answer": "OVERT",
        "direction": "down"
      },
      {
        "number": 45,
        "clue": "Ranger's domain",
        "answer": "FOREST",
        "direction": "down"
      },
      {
        "number": 46,
        "clue": "\"Leave this to me\"",
        "answer": "IMONIT",
        "direction": "down"
      },
      {
        "number": 47,
        "clue": "Is all over the map",
        "answer": "VARIES",
        "direction": "down"
      },
      {
        "number": 49,
        "clue": "Showers affection (on)",
        "answer": "DOTES",
        "direction": "down"
      },
      {
        "number": 51,
        "clue": "Like the Vietnamese language",
        "answer": "TONAL",
        "direction": "down"
      },
      {
        "number": 52,
        "clue": "Rod Flanders's brother on \"The Simpsons\"",
        "answer": "TODD",
        "direction": "down"
      },
      {
        "number": 53,
        "clue": "Like some traditions",
        "answer": "ORAL",
        "direction": "down"
      },
      {
        "number": 54,
        "clue": "Bamako's land",
        "answer": "MALI",
        "direction": "down"
      },
      {
        "number": 55,
        "clue": "Sign sought by one reading tea leaves",
        "answer": "OMEN",
        "direction": "down"
      },
      {
        "number": 56,
        "clue": "Muck",
        "answer": "MIRE",
        "direction": "down"
      },
      {
        "number": 57,
        "clue": "Major tennis tournament",
        "answer": "OPEN",
        "direction": "down"
      },
      {
        "number": 58,
        "clue": "Pause indicator in sheet music",
        "answer": "REST",
        "direction": "down"
      }
    ]
  },
  "timestamp": "2026-01-29T04:31:01.423Z"
}